README.md
setup.py
polygon_etl.egg-info/PKG-INFO
polygon_etl.egg-info/SOURCES.txt
polygon_etl.egg-info/dependency_links.txt
polygon_etl.egg-info/entry_points.txt
polygon_etl.egg-info/requires.txt
polygon_etl.egg-info/top_level.txt
polygonetl/__init__.py
polygonetl/__main__.py
polygonetl/atomic_counter.py
polygonetl/csv_utils.py
polygonetl/erc20_abi.py
polygonetl/exporters.py
polygonetl/json_rpc_requests.py
polygonetl/mainnet_daofork_state_changes.py
polygonetl/mainnet_genesis_alloc.py
polygonetl/misc_utils.py
polygonetl/progress_logger.py
polygonetl/thread_local_proxy.py
polygonetl/utils.py
polygonetl/web3_utils.py
polygonetl/cli/__init__.py
polygonetl/cli/export_all.py
polygonetl/cli/export_blocks_and_transactions.py
polygonetl/cli/export_contracts.py
polygonetl/cli/export_geth_traces.py
polygonetl/cli/export_receipts_and_logs.py
polygonetl/cli/export_token_transfers.py
polygonetl/cli/export_tokens.py
polygonetl/cli/export_traces.py
polygonetl/cli/extract_contracts.py
polygonetl/cli/extract_csv_column.py
polygonetl/cli/extract_field.py
polygonetl/cli/extract_geth_traces.py
polygonetl/cli/extract_token_transfers.py
polygonetl/cli/extract_tokens.py
polygonetl/cli/filter_items.py
polygonetl/cli/get_block_range_for_date.py
polygonetl/cli/get_block_range_for_timestamps.py
polygonetl/cli/get_keccak_hash.py
polygonetl/cli/stream.py
polygonetl/domain/__init__.py
polygonetl/domain/block.py
polygonetl/domain/contract.py
polygonetl/domain/geth_trace.py
polygonetl/domain/receipt.py
polygonetl/domain/receipt_log.py
polygonetl/domain/token.py
polygonetl/domain/token_transfer.py
polygonetl/domain/trace.py
polygonetl/domain/transaction.py
polygonetl/enumeration/__init__.py
polygonetl/enumeration/entity_type.py
polygonetl/executors/__init__.py
polygonetl/executors/batch_work_executor.py
polygonetl/executors/bounded_executor.py
polygonetl/executors/fail_safe_executor.py
polygonetl/jobs/__init__.py
polygonetl/jobs/export_all_common.py
polygonetl/jobs/export_blocks_job.py
polygonetl/jobs/export_contracts_job.py
polygonetl/jobs/export_geth_traces_job.py
polygonetl/jobs/export_receipts_job.py
polygonetl/jobs/export_token_transfers_job.py
polygonetl/jobs/export_tokens_job.py
