Metadata-Version: 2.1
Name: polygon-etl
Version: 0.2.0
Summary: Tools for exporting Polygon blockchain data to CSV or JSON
Home-page: https://github.com/blockchain-etl/polygon-etl
Author: Evgeny Medvedev
Author-email: evge.medvedev@gmail.com
License: UNKNOWN
Project-URL: Bug Reports, https://github.com/blockchain-etl/polygon-etl/issues
Project-URL: Source, https://github.com/blockchain-etl/polygon-etl
Keywords: polygon
Platform: UNKNOWN
Classifier: Development Status :: 5 - Production/Stable
Classifier: Intended Audience :: Developers
Classifier: License :: OSI Approved :: MIT License
Classifier: Programming Language :: Python :: 3
Classifier: Programming Language :: Python :: 3.6
Classifier: Programming Language :: Python :: 3.7
Classifier: Programming Language :: Python :: 3.8
Classifier: Programming Language :: Python :: 3.9
Requires-Python: >=3.6,<3.10
Provides-Extra: streaming
